<?xml version="1.0" encoding="UTF-8"?>
<objects serializationModel="Studio.02.02.00">
	<object class="AudioFile" id="{74561796-97d3-45ac-b47f-d0e5692249eb}">
		<property name="assetPath">
			<value>Assets/Vehicles/Car Engine/veh_car_engine_190E_06723.ogg</value>
		</property>
		<property name="frequencyInKHz">
			<value>48</value>
		</property>
		<property name="channelCount">
			<value>1</value>
		</property>
		<property name="length">
			<value>0.51433333333333331</value>
		</property>
		<relationship name="masterAssetFolder">
			<destination>{8110e1b6-8459-4827-adc8-e8be1a639aed}</destination>
		</relationship>
	</object>
</objects>
